Cahier-0.1.1.dist-info/DESCRIPTION.rst
Cahier-0.1.1.dist-info/METADATA
Cahier-0.1.1.dist-info/RECORD
Cahier-0.1.1.dist-info/WHEEL
Cahier-0.1.1.dist-info/entry_points.txt
Cahier-0.1.1.dist-info/metadata.json
Cahier-0.1.1.dist-info/top_level.txt
cahier/__init__.py
cahier/config.py
cahier/errors.py
cahier/io.py
cahier/main.py
cahier/path.py
cahier/cmd_plugins/__init__.py
cahier/cmd_plugins/cd.py
cahier/cmd_plugins/date.py
cahier/cmd_plugins/git.py
cahier/cmd_plugins/ikiwiki.py
