Metadata-Version: 2.0
Name: Cahier
Version: 0.1.1
Summary: One-directory-a-day calendar management
Home-page: https://git.framasoft.org/spalax/cahier
Author: Louis Paternault
Author-email: spalax@gresille.org
License: GPLv3 or any later version
Platform: UNKNOWN
Classifier: Development Status :: 5 - Production/Stable
Classifier: Environment :: Console
Classifier: License :: OSI Approved :: GNU General Public License v3 or later (GPLv3+)
Classifier: Intended Audience :: End Users/Desktop
Classifier: Operating System :: OS Independent
Classifier: Programming Language :: Python
Classifier: Programming Language :: Python :: 3
Classifier: Programming Language :: Python :: 3.4
Classifier: Programming Language :: Python :: 3.5
Classifier: Topic :: Utilities
